leistungsbot/Bot.py
leistungsbot/BotHelper.py
leistungsbot/BotScheduler.py
leistungsbot/__main__.py
leistungsbot/_version.py
leistungsbot/google_place.py
leistungsbot/leistungs_config.py
leistungsbot/leistungs_db.py
leistungsbot/leistungs_returns.py
leistungsbot/resources/responisibility.gif
leistungsbot/resources/sneaky.gif
leistungsbot-1.1.4.dist-info/LICENSE.md
leistungsbot-1.1.4.dist-info/METADATA
leistungsbot-1.1.4.dist-info/WHEEL
leistungsbot-1.1.4.dist-info/entry_points.txt
leistungsbot-1.1.4.dist-info/RECORD
