Metadata-Version: 2.3
Name: leistungsbot
Version: 1.1.4
Summary: 
Author: EckPhi
Requires-Python: >=3.11,<4.0
Classifier: Programming Language :: Python :: 3
Classifier: Programming Language :: Python :: 3.11
Classifier: Programming Language :: Python :: 3.12
Classifier: Programming Language :: Python :: 3.13
Requires-Dist: confuse (>=2.0.1,<3.0.0)
Requires-Dist: googlemaps (>=4.10.0,<5.0.0)
Requires-Dist: mysql-connector-python (>=9.0.0,<10.0.0)
Requires-Dist: platformdirs (>=4.2.2,<5.0.0)
Requires-Dist: pyTelegramBotAPI (>=4.5.0,<5.0.0)
Requires-Dist: python-telegram-bot-calendar (>=1.0.5,<2.0.0)
Requires-Dist: pyyaml (>=6.0.2,<7.0.0)
Requires-Dist: requests (>=2.32.3,<3.0.0)
Requires-Dist: schedule (>=1.2.2,<2.0.0)
Requires-Dist: urllib3 (>=2.2.2,<3.0.0)
